{
  "id": "c077",
  "program": "(lambda (flatten (zip $0 (reverse $0))))",
  "data": [
    { "i": [76, 38, 66, 5, 3, 68], "o": [76, 68, 38, 3, 66, 5, 5, 66, 3, 38, 68, 76] },
    { "i": [78, 9, 54, 23, 21], "o": [78, 21, 9, 23, 54, 54, 23, 9, 21, 78] },
    { "i": [59, 90], "o": [59, 90, 90, 59] },
    { "i": [83], "o": [83, 83] },
    { "i": [93, 50, 81], "o": [93, 81, 50, 50, 81, 93] },
    { "i": [1, 15, 28, 4], "o": [1, 4, 15, 28, 28, 15, 4, 1] },
    { "i": [64, 98, 27, 26, 32], "o": [64, 32, 98, 26, 27, 27, 26, 98, 32, 64] },
    { "i": [80, 2, 61, 24, 37, 8], "o": [80, 8, 2, 37, 61, 24, 24, 61, 37, 2, 8, 80] },
    { "i": [7, 16, 82, 19, 55, 6], "o": [7, 6, 16, 55, 82, 19, 19, 82, 55, 16, 6, 7] },
    { "i": [62, 11, 88], "o": [62, 88, 11, 11, 88, 62] },
    { "i": [96, 51, 94, 91], "o": [96, 91, 51, 94, 94, 51, 91, 96] }
  ]
}