{
  "id": "c086",
  "program": "(lambda (filter (lambda (> $0 (first $1))) $0))",
  "data": [
    { "i": [9, 46, 5, 70, 46, 3, 66, 43, 7], "o": [46, 70, 46, 66, 43] },
    { "i": [6, 71, 97, 98, 0, 64, 60, 3, 0], "o": [71, 97, 98, 64, 60] },
    { "i": [61, 42, 5, 1, 0, 54, 87, 77, 9], "o": [87, 77] },
    { "i": [4, 47, 96, 24, 88, 55, 38, 13, 26, 9], "o": [47, 96, 24, 88, 55, 38, 13, 26, 9] },
    { "i": [79, 7, 32, 2, 8, 86, 93, 51, 95, 5], "o": [86, 93, 95] },
    { "i": [77, 20, 26, 99, 12, 81, 27, 90, 90, 77], "o": [99, 81, 90, 90] },
    { "i": [73, 39, 94, 5, 95, 23, 73, 84, 66], "o": [94, 95, 84] },
    { "i": [72, 17, 4, 50, 80, 17, 37, 29, 57], "o": [80] },
    { "i": [31, 30, 53, 74, 9, 12, 12, 5, 31, 31], "o": [53, 74] },
    { "i": [7, 34, 6, 7, 35, 67, 4, 15, 28, 1], "o": [34, 35, 67, 15, 28] },
    { "i": [30, 38, 7, 2, 4, 58, 6, 62, 10, 83], "o": [38, 58, 62, 83] }
  ]
}